Jevis/__init__.py
Jevis-0.1.0.dist-info/LICENSE
Jevis-0.1.0.dist-info/METADATA
Jevis-0.1.0.dist-info/WHEEL
Jevis-0.1.0.dist-info/top_level.txt
Jevis-0.1.0.dist-info/RECORD
