Metadata-Version: 2.1
Name: Jevis
Version: 0.1.0
Summary: A powerful package
Home-page: https://github.com/pypa/sampleproject
Author: Jiang ChengJun
Author-email: jcj1947725596@hotmail.com
Classifier: Programming Language :: Python :: 3
Classifier: License :: OSI Approved :: MIT License
Classifier: Operating System :: OS Independent
